Metadata-Version: 2.1
Name: ll2location
Version: 0.0.3
Summary: ll2location
Home-page: https://github.com/truong-xuan-linh/ll2location
Author: Trương Xuân Linh
Author-email: truonglinh1342001@gmail.com
Classifier: Programming Language :: Python :: 3
Classifier: License :: OSI Approved :: MIT License
Classifier: Operating System :: OS Independent
License-File: LICENSE
